relics/__init__.py
relics/filesystem_constants.py
relics/utils.py
relics/version.py
relics/data/__init__.py
relics/data/relics_mapping.yaml
relics-0.0.6.dist-info/licenses/LICENSE
relics-0.0.6.dist-info/METADATA
relics-0.0.6.dist-info/WHEEL
relics-0.0.6.dist-info/top_level.txt
relics-0.0.6.dist-info/RECORD
